hdit/__init__.py
hdit/modules/__init__.py
hdit/modules/flags.py
hdit/modules/flops.py
hdit/modules/sampling.py
hdit/modules/supplies.py
hdit/modules/things.py
hdit/modules/attention/__init__.py
hdit/modules/attention/axial_rope.py
hdit/modules/attention/basic_core.py
hdit/modules/attention/neighborhood_attention.py
hdit/modules/attention/self_attention.py
hdit/modules/attention/shifted_self_attention.py
hdit/modules/models/__init__.py
hdit/modules/models/hourglass_diffusion_transformer/__init__.py
hdit/modules/models/hourglass_diffusion_transformer/core.py
hdit/modules/models/hourglass_diffusion_transformer/layers.py
hdit/utils/__init__.py
hdit/utils/args_context.py
hdit-0.0.1b6.dist-info/licenses/LICENSE
hdit-0.0.1b6.dist-info/METADATA
hdit-0.0.1b6.dist-info/WHEEL
hdit-0.0.1b6.dist-info/top_level.txt
hdit-0.0.1b6.dist-info/RECORD
